odoo/addons/stock_production_lot_expiry_state/README.rst
odoo/addons/stock_production_lot_expiry_state/__init__.py
odoo/addons/stock_production_lot_expiry_state/__manifest__.py
odoo/addons/stock_production_lot_expiry_state/data/cron.xml
odoo/addons/stock_production_lot_expiry_state/i18n/stock_production_lot_expiry_state.pot
odoo/addons/stock_production_lot_expiry_state/models/__init__.py
odoo/addons/stock_production_lot_expiry_state/models/stock_production_lot.py
odoo/addons/stock_production_lot_expiry_state/readme/CONTRIBUTORS.rst
odoo/addons/stock_production_lot_expiry_state/readme/CREDITS.rst
odoo/addons/stock_production_lot_expiry_state/readme/DESCRIPTION.rst
odoo/addons/stock_production_lot_expiry_state/readme/USAGE.rst
odoo/addons/stock_production_lot_expiry_state/static/description/icon.png
odoo/addons/stock_production_lot_expiry_state/static/description/index.html
odoo/addons/stock_production_lot_expiry_state/views/stock_production_lot_views.xml
odoo11_addon_stock_production_lot_expiry_state-11.0.1.0.0.99.dev5.dist-info/METADATA
odoo11_addon_stock_production_lot_expiry_state-11.0.1.0.0.99.dev5.dist-info/WHEEL
odoo11_addon_stock_production_lot_expiry_state-11.0.1.0.0.99.dev5.dist-info/top_level.txt
odoo11_addon_stock_production_lot_expiry_state-11.0.1.0.0.99.dev5.dist-info/RECORD
