Metadata-Version: 2.1
Name: odoo11-addon-stock-production-lot-expiry-state
Version: 11.0.1.0.0.99.dev5
Summary: Add a state field to expiring lot/SN
Home-page: https://github.com/OCA/stock-logistics-warehouse
Author: Open Source Integrators, Odoo Community Association (OCA)
Author-email: support@odoo-community.org
License: AGPL-3
Platform: UNKNOWN
Classifier: Programming Language :: Python
Classifier: Framework :: Odoo
Classifier: Framework :: Odoo :: 11.0
Classifier: License :: OSI Approved :: GNU Affero General Public License v3
Classifier: Development Status :: 4 - Beta
Requires-Python: >=2.7, !=3.0.*, !=3.1.*, !=3.2.*, !=3.3.*, !=3.4.*
Requires-Dist: odoo <11.1dev,>=11.0a
